odoo8_addon_document_page_quality_manual-8.0.1.0.0-py2.7-nspkg.pth
odoo8_addon_document_page_quality_manual-8.0.1.0.0.dist-info/top_level.txt
odoo8_addon_document_page_quality_manual-8.0.1.0.0.dist-info/WHEEL
odoo8_addon_document_page_quality_manual-8.0.1.0.0.dist-info/RECORD
odoo8_addon_document_page_quality_manual-8.0.1.0.0.dist-info/metadata.json
odoo8_addon_document_page_quality_manual-8.0.1.0.0.dist-info/DESCRIPTION.rst
odoo8_addon_document_page_quality_manual-8.0.1.0.0.dist-info/METADATA
odoo8_addon_document_page_quality_manual-8.0.1.0.0.dist-info/namespace_packages.txt
odoo_addons/document_page_quality_manual/__openerp__.py
odoo_addons/document_page_quality_manual/__init__.py
odoo_addons/document_page_quality_manual/README.rst
odoo_addons/document_page_quality_manual/migrations/7.0.1.0/pre-migration.py
odoo_addons/document_page_quality_manual/i18n/ja.po
odoo_addons/document_page_quality_manual/i18n/lv.po
odoo_addons/document_page_quality_manual/i18n/zh_CN.po
odoo_addons/document_page_quality_manual/i18n/oc.po
odoo_addons/document_page_quality_manual/i18n/ru.po
odoo_addons/document_page_quality_manual/i18n/pt.po
odoo_addons/document_page_quality_manual/i18n/it.po
odoo_addons/document_page_quality_manual/i18n/es.po
odoo_addons/document_page_quality_manual/i18n/ar.po
odoo_addons/document_page_quality_manual/i18n/ro.po
odoo_addons/document_page_quality_manual/i18n/tr.po
odoo_addons/document_page_quality_manual/i18n/hr.po
odoo_addons/document_page_quality_manual/i18n/bg.po
odoo_addons/document_page_quality_manual/i18n/hu.po
odoo_addons/document_page_quality_manual/i18n/gl.po
odoo_addons/document_page_quality_manual/i18n/ca.po
odoo_addons/document_page_quality_manual/i18n/es_CR.po
odoo_addons/document_page_quality_manual/i18n/sl.po
odoo_addons/document_page_quality_manual/i18n/sr@latin.po
odoo_addons/document_page_quality_manual/i18n/cs.po
odoo_addons/document_page_quality_manual/i18n/nb.po
odoo_addons/document_page_quality_manual/i18n/da.po
odoo_addons/document_page_quality_manual/i18n/mn.po
odoo_addons/document_page_quality_manual/i18n/nl.po
odoo_addons/document_page_quality_manual/i18n/de.po
odoo_addons/document_page_quality_manual/i18n/vi.po
odoo_addons/document_page_quality_manual/i18n/fr.po
odoo_addons/document_page_quality_manual/i18n/document_page_quality_manual.pot
odoo_addons/document_page_quality_manual/i18n/pt_BR.po
odoo_addons/document_page_quality_manual/i18n/es_VE.po
